LICENSE
MANIFEST.in
README.md
setup.cfg
setup.py
concierge-freshdesk-plugin/__init__.py
concierge-freshdesk-plugin/admin.py
concierge-freshdesk-plugin/apps.py
concierge-freshdesk-plugin/models.py
concierge-freshdesk-plugin/settings.py
concierge-freshdesk-plugin/tests.py
concierge-freshdesk-plugin/views.py
concierge-freshdesk-plugin/migrations/__init__.py
concierge_freshdesk_plugin/__init__.py
concierge_freshdesk_plugin/admin.py
concierge_freshdesk_plugin/apps.py
concierge_freshdesk_plugin/models.py
concierge_freshdesk_plugin/settings.py
concierge_freshdesk_plugin/tests.py
concierge_freshdesk_plugin/urls.py
concierge_freshdesk_plugin/views.py
concierge_freshdesk_plugin.egg-info/PKG-INFO
concierge_freshdesk_plugin.egg-info/SOURCES.txt
concierge_freshdesk_plugin.egg-info/dependency_links.txt
concierge_freshdesk_plugin.egg-info/top_level.txt
concierge_freshdesk_plugin/migrations/0001_initial.py
concierge_freshdesk_plugin/migrations/0002_configuration_url.py
concierge_freshdesk_plugin/migrations/0003_auto_20180913_1332.py
concierge_freshdesk_plugin/migrations/0004_auto_20180917_1020.py
concierge_freshdesk_plugin/migrations/0005_auto_20180917_1024.py
concierge_freshdesk_plugin/migrations/0006_auto_20180917_1436.py
concierge_freshdesk_plugin/migrations/__init__.py
concierge_freshdesk_plugin/tests/__init__.py
concierge_freshdesk_plugin/tests/conftest.py
concierge_freshdesk_plugin/tests/test_configuration.py