Metadata-Version: 1.2
Name: concierge-freshdesk-plugin
Version: 0.1
Summary: The Government of Canada freshdesk for Concierge
Home-page: https://github.com/gctools-outilsgc/concierge-freshdesk-plugin
Maintainer: GCTools Team
License: OSI Approved :: European Union Public Licence 1.1 (EUPL 1.1)
Platform: UNKNOWN
Classifier: Environment :: Web Environment
Classifier: Intended Audience :: Developers
Classifier: Operating System :: OS Independent
Classifier: Programming Language :: Python
Classifier: Programming Language :: Python :: 3.5
Classifier: Programming Language :: Python :: 3.6
